[
  {
    "id": "GH1000001",
    "nombre": "Marlon ToDo",
    "correo": "marlon@ToDo.com",
    "secret": "mar#lon#secret"
  },
  {
    "id": "GH1000002",
    "nombre": "Víctor ToDo",
    "correo": "victor@ToDo.com",
    "secret": "vic#tor#secret"
  },
  {
    "id": "GH1000003",
    "nombre": "Jazmín ToDo",
    "correo": "jazmin@ToDo.com",
    "secret": "jaz#min#secret"
  },
  {
    "id": "GH1000004",
    "nombre": "Daniel ToDo",
    "correo": "daniel@ToDo.com",
    "secret": "dan#iel#secret"
  },
  {
    "id": "1625204836051-933018",
    "nombre": "prueba1",
    "correo": "prueba1@ToDo.com",
    "secret": "pru#eba1#secret"
  },
  {
    "id": "1625205084681-455089",
    "nombre": "prueba2",
    "correo": "prueba2@ToDo.com",
    "secret": "pru#eba2#secret"
  },
  {
    "id": "1625206571463-735079",
    "nombre": "prueba3",
    "correo": "prueba3@ToDo.com",
    "secret": "pru#eba3#secret"
  },
  {
    "id": "1625206838745-380122",
    "nombre": "prueba4",
    "correo": "prueba4@ToDo.com",
    "secret": "pru#eba4#secret"
  },
  {
    "id": "1625207020290-359360",
    "nombre": "prueba5",
    "correo": "prueba5@ToDo.com",
    "secret": "pru#eba5#secret"
  },
  {
    "id": "1625207179281-403857",
    "nombre": "prueba6",
    "correo": "prueba6@ToDo.com",
    "secret": "pru#eba6#secret"
  },
  {
    "id": "1625207485707-983738",
    "nombre": "prueba7",
    "correo": "prueba7@ToDo.com",
    "secret": "pru#eba7#secret"
  },
  {
    "id": "1625207675198-624392",
    "nombre": "prueba8",
    "correo": "prueba8@ToDo.com",
    "secret": "pru#eba8#secret"
  }
]